genai_wrapper/__init__.py
genai_wrapper/wrapper.py
genai_wrapper/aicore/__init__.py
genai_wrapper/aicore/aicore.py
genai_wrapper/comm/__init__.py
genai_wrapper/comm/base_comm.py
genai_wrapper/comm/chat.py
genai_wrapper/comm/embed.py
genai_wrapper/config/__init__.py
genai_wrapper/config/config.py
genai_wrapper/data_objects/__init__.py
genai_wrapper/data_objects/chat_object.py
genai_wrapper/data_objects/vector_object.py
genai_wrapper/exceptions/__init__.py
genai_wrapper/exceptions/exceptions.py
genai_wrapper/hanadb/__init__.py
genai_wrapper/hanadb/hanadb.py
genai_wrapper-0.0.9.dist-info/LICENSE
genai_wrapper-0.0.9.dist-info/METADATA
genai_wrapper-0.0.9.dist-info/WHEEL
genai_wrapper-0.0.9.dist-info/top_level.txt
genai_wrapper-0.0.9.dist-info/RECORD
