Metadata-Version: 2.1
Name: genai-wrapper
Version: 0.0.9
Summary: A user-friendly GenAI wrapper that leverages SAP's AI Core to seamlessly translate requests into LLM calls.
Home-page: UNKNOWN
Author: Praveen Nair
Author-email: 
License: MIT
Project-URL: Source Repository, https://github.com/praveen-nair/genai_wrapper
Project-URL: Issues, https://github.com/praveen-nair/genai_wrapper/issues
Platform: UNKNOWN
License-File: LICENSE
Requires-Dist: ai-api-client-sdk (>=2.1.4)
Requires-Dist: ai-core-sdk (>=2.3.11)
Requires-Dist: hdbcli (>=2.21.28)
